MANIFEST.in
README.txt
interfaces.py
setup.py
test_wordish.py
wordish.py
examples/lvm.rst
html/sources/index.txt
html/sources/interfaces.txt
html/sources/methods.txt
html/sources/roadmap.txt
html/sources/write.txt
html/static/basic.css
html/static/contents.png
html/static/doctools.js
html/static/file.png
html/static/jquery.js
html/static/minus.png
html/static/navigation.png
html/static/plus.png
html/static/pygments.css
html/static/searchtools.js
html/static/sphinxdoc.css
wordish.egg-info/PKG-INFO
wordish.egg-info/SOURCES.txt
wordish.egg-info/dependency_links.txt
wordish.egg-info/top_level.txt