Metadata-Version: 1.1
Name: wordish
Version: 1.0.2
Summary: Parses a shell session, test the commands compare the outputs
Home-page: UNKNOWN
Author: Jean Daniel Browne
Author-email: jeandaniel.browne@gmail.com
License: GPL
Platform: UNKNOWN
Classifier: Development Status :: 4 - Beta
Classifier: Environment :: Console
Classifier: Intended Audience :: Developers
Classifier: Intended Audience :: Education
Classifier: Intended Audience :: System Administrators
Classifier: License :: OSI Approved :: GNU General Public License (GPL)
Classifier: Operating System :: Unix
Classifier: Programming Language :: Python :: 2
Classifier: Programming Language :: Unix Shell
Classifier: Topic :: Documentation
Classifier: Topic :: Education
Classifier: Topic :: Software Development :: Testing
Classifier: Topic :: Utilities
Requires: docutils (>=0.5)
